{
    "Points Collision" : {
        "Main Characters" : {
            "Mask Dude" : {
                "Double Jump" : [[12, 4], 
                                 [24, 4],
                                 [24, 10],
                                 [24, 28],
                                 [21, 31],
                                 [10, 31],
                                 [8, 28],
                                 [5, 10]],
                "Jump" : [[12, 4], 
                          [24, 4],
                          [24, 10],
                          [24, 28],
                          [21, 31],
                          [10, 31],
                          [8, 28],
                          [5, 10]],
                "Idle" : [[12, 4],
                          [24, 4],
                          [24, 10],
                          [24, 28],
                          [21, 31],
                          [10, 31],
                          [8, 28],
                          [5, 10]],
                "Run" : [[12, 0], 
                         [24, 0],
                         [24, 10],
                         [24, 28],
                         [21, 31],
                         [10, 31],
                         [8, 28],
                         [5, 10]],
                "Fall" : [[12, 4],
                          [24, 4],
                          [24, 10],
                          [24, 28],
                          [21, 31],
                          [10, 31],
                          [8, 28],
                          [5, 10]],
                "Hit" : [[12, 4],
                          [24, 4],
                          [24, 10],
                          [24, 28],
                          [21, 31],
                          [10, 31],
                          [8, 28],
                          [5, 10]],
                "Wall Jump" : [[12, 4],
                          [24, 4],
                          [24, 10],
                          [24, 28],
                          [21, 31],
                          [10, 31],
                          [7, 28],
                          [7, 17]]
            },
            "Ninja Frog" : {
                "Double Jump" : [[12, 4], 
                                 [24, 4],
                                 [24, 10],
                                 [24, 28],
                                 [21, 31],
                                 [10, 31],
                                 [8, 28],
                                 [5, 10]],
                "Jump" : [[12, 4], 
                          [24, 4],
                          [24, 10],
                          [24, 28],
                          [21, 31],
                          [10, 31],
                          [8, 28],
                          [5, 10]],
                "Idle" : [[12, 4],
                          [24, 4],
                          [24, 10],
                          [24, 28],
                          [21, 31],
                          [10, 31],
                          [8, 28],
                          [5, 10]],
                "Run" : [[12, 0], 
                         [24, 0],
                         [24, 10],
                         [24, 28],
                         [21, 31],
                         [10, 31],
                         [8, 28],
                         [5, 10]],
                "Fall" : [[12, 4],
                          [24, 4],
                          [24, 10],
                          [24, 28],
                          [21, 31],
                          [10, 31],
                          [8, 28],
                          [5, 10]],
                "Hit" : [[12, 4],
                          [24, 4],
                          [24, 10],
                          [24, 28],
                          [21, 31],
                          [10, 31],
                          [8, 28],
                          [5, 10]],
                "Wall Jump" : [[12, 4],
                          [24, 4],
                          [24, 10],
                          [24, 28],
                          [21, 31],
                          [10, 31],
                          [7, 28],
                          [7, 17]]
            },
            "Pink Man" : {
                "Double Jump" : [[12, 4], 
                                 [24, 4],
                                 [24, 10],
                                 [24, 28],
                                 [21, 31],
                                 [10, 31],
                                 [8, 28],
                                 [5, 10]],
                "Jump" : [[12, 4], 
                          [24, 4],
                          [24, 10],
                          [24, 28],
                          [21, 31],
                          [10, 31],
                          [8, 28],
                          [5, 10]],
                "Idle" : [[12, 4],
                          [24, 4],
                          [24, 10],
                          [24, 28],
                          [21, 31],
                          [10, 31],
                          [8, 28],
                          [5, 10]],
                "Run" : [[12, 0], 
                         [24, 0],
                         [24, 10],
                         [24, 28],
                         [21, 31],
                         [10, 31],
                         [8, 28],
                         [5, 10]],
                "Fall" : [[12, 4],
                          [24, 4],
                          [24, 10],
                          [24, 28],
                          [21, 31],
                          [10, 31],
                          [8, 28],
                          [5, 10]],
                "Hit" : [[12, 4],
                          [24, 4],
                          [24, 10],
                          [24, 28],
                          [21, 31],
                          [10, 31],
                          [8, 28],
                          [5, 10]],
                "Wall Jump" : [[12, 4],
                          [24, 4],
                          [24, 10],
                          [24, 28],
                          [21, 31],
                          [10, 31],
                          [7, 28],
                          [7, 17]]
            },
            "Virtual Guy" : {
                "Double Jump" : [[12, 4], 
                                 [24, 4],
                                 [24, 10],
                                 [24, 28],
                                 [21, 31],
                                 [10, 31],
                                 [8, 28],
                                 [5, 10]],
                "Jump" : [[12, 4], 
                          [24, 4],
                          [24, 10],
                          [24, 28],
                          [21, 31],
                          [10, 31],
                          [8, 28],
                          [5, 10]],
                "Idle" : [[12, 4],
                          [24, 4],
                          [24, 10],
                          [24, 28],
                          [21, 31],
                          [10, 31],
                          [8, 28],
                          [5, 10]],
                "Run" : [[12, 0], 
                         [24, 0],
                         [24, 10],
                         [24, 28],
                         [21, 31],
                         [10, 31],
                         [8, 28],
                         [5, 10]],
                "Fall" : [[12, 4],
                          [24, 4],
                          [24, 10],
                          [24, 28],
                          [21, 31],
                          [10, 31],
                          [8, 28],
                          [5, 10]],
                "Hit" : [[12, 4],
                          [24, 4],
                          [24, 10],
                          [24, 28],
                          [21, 31],
                          [10, 31],
                          [8, 28],
                          [5, 10]],
                "Wall Jump" : [[12, 4],
                          [24, 4],
                          [24, 10],
                          [24, 28],
                          [21, 31],
                          [10, 31],
                          [7, 28],
                          [7, 17]]
            }
        }
    }
}