{
    "Points Collision" : {
        "Main Characters" : {
            "Mask Dude" : {
                "Double Jump" : [[12, 4], 
                                 [24, 4],
                                 [25, 10],
                                 [25, 24],
                                 [21, 31],
                                 [10, 31],
                                 [8, 24],
                                 [7, 10]],
                "Jump" : [[12, 4], 
                          [24, 4],
                          [25, 10],
                          [25, 24],
                          [21, 31],
                          [10, 31],
                          [8, 24],
                          [7, 10]],
                "Idle" : [[12, 4],
                          [24, 4],
                          [25, 10],
                          [25, 24],
                          [21, 31],
                          [10, 31],
                          [8, 24],
                          [7, 10]],
                "Run" : [[12, 4], 
                         [24, 4],
                         [25, 10],
                         [25, 24],
                         [21, 31],
                         [10, 31],
                         [8, 24],
                         [7, 10]],
                "Fall" : [[12, 4],
                          [24, 4],
                          [25, 10],
                          [25, 24],
                          [21, 31],
                          [10, 31],
                          [8, 24],
                          [7, 10]],
                "Hit" : [[12, 4],
                          [24, 4],
                          [25, 10],
                          [25, 24],
                          [21, 31],
                          [10, 31],
                          [8, 24],
                          [7, 10]],
                "Wall Jump" : [[12, 4],
                          [24, 4],
                          [25, 10],
                          [25, 24],
                          [21, 31],
                          [10, 31],
                          [7, 24],
                          [7, 17]]
            },
            "Ninja Frog" : {
                "Double Jump" : [[12, 4], 
                                 [24, 4],
                                 [25, 10],
                                 [25, 24],
                                 [21, 31],
                                 [10, 31],
                                 [8, 24],
                                 [7, 10]],
                "Jump" : [[12, 4], 
                          [24, 4],
                          [25, 10],
                          [25, 24],
                          [21, 31],
                          [10, 31],
                          [8, 24],
                          [7, 10]],
                "Idle" : [[12, 4],
                          [24, 4],
                          [25, 10],
                          [25, 24],
                          [21, 31],
                          [10, 31],
                          [8, 24],
                          [7, 10]],
                "Run" : [[12, 4], 
                         [24, 4],
                         [25, 10],
                         [25, 24],
                         [21, 31],
                         [10, 31],
                         [8, 24],
                         [7, 10]],
                "Fall" : [[12, 4],
                          [24, 4],
                          [25, 10],
                          [25, 24],
                          [21, 31],
                          [10, 31],
                          [8, 24],
                          [7, 10]],
                "Hit" : [[12, 4],
                          [24, 4],
                          [25, 10],
                          [25, 24],
                          [21, 31],
                          [10, 31],
                          [8, 24],
                          [7, 10]],
                "Wall Jump" : [[12, 4],
                          [24, 4],
                          [25, 10],
                          [25, 24],
                          [21, 31],
                          [10, 31],
                          [7, 24],
                          [7, 17]]
            },
            "Pink Man" : {
                "Double Jump" : [[12, 4], 
                                 [24, 4],
                                 [25, 10],
                                 [25, 24],
                                 [21, 31],
                                 [10, 31],
                                 [8, 24],
                                 [7, 10]],
                "Jump" : [[12, 4], 
                          [24, 4],
                          [25, 10],
                          [25, 24],
                          [21, 31],
                          [10, 31],
                          [8, 24],
                          [7, 10]],
                "Idle" : [[12, 4],
                          [24, 4],
                          [25, 10],
                          [25, 24],
                          [21, 31],
                          [10, 31],
                          [8, 24],
                          [7, 10]],
                "Run" : [[12, 4], 
                         [24, 4],
                         [25, 10],
                         [25, 24],
                         [21, 31],
                         [10, 31],
                         [8, 24],
                         [7, 10]],
                "Fall" : [[12, 4],
                          [24, 4],
                          [25, 10],
                          [25, 24],
                          [21, 31],
                          [10, 31],
                          [8, 24],
                          [7, 10]],
                "Hit" : [[12, 4],
                          [24, 4],
                          [25, 10],
                          [25, 24],
                          [21, 31],
                          [10, 31],
                          [8, 24],
                          [7, 10]],
                "Wall Jump" : [[12, 4],
                          [24, 4],
                          [25, 10],
                          [25, 24],
                          [21, 31],
                          [10, 31],
                          [7, 24],
                          [7, 17]]
            },
            "Virtual Guy" : {
                "Double Jump" : [[12, 4], 
                                 [24, 4],
                                 [25, 10],
                                 [25, 24],
                                 [21, 31],
                                 [10, 31],
                                 [8, 24],
                                 [7, 10]],
                "Jump" : [[12, 4], 
                          [24, 4],
                          [25, 10],
                          [25, 24],
                          [21, 31],
                          [10, 31],
                          [8, 24],
                          [7, 10]],
                "Idle" : [[12, 4],
                          [24, 4],
                          [25, 10],
                          [25, 24],
                          [21, 31],
                          [10, 31],
                          [8, 24],
                          [7, 10]],
                "Run" : [[12, 4], 
                         [24, 4],
                         [25, 10],
                         [25, 24],
                         [21, 31],
                         [10, 31],
                         [8, 24],
                         [7, 10]],
                "Fall" : [[12, 4],
                          [24, 4],
                          [25, 10],
                          [25, 24],
                          [21, 31],
                          [10, 31],
                          [8, 24],
                          [7, 10]],
                "Hit" : [[12, 4],
                          [24, 4],
                          [25, 10],
                          [25, 24],
                          [21, 31],
                          [10, 31],
                          [8, 24],
                          [7, 10]],
                "Wall Jump" : [[12, 4],
                          [24, 4],
                          [25, 10],
                          [25, 24],
                          [21, 31],
                          [10, 31],
                          [7, 24],
                          [7, 17]]
            }
        },
        "Traps" : {
            "Trampoline" : {
                "Idle" : [[[2, 17], [22, 7]]],
                "Jump" : [[[2, 17], [22, 7]], 
                            [[2, 17], [22, 7]], 
                            [[2, 17], [22, 7]], 
                            [[2, 17], [22, 7]], 
                            [[2, 17], [22, 7]], 
                            [[2, 17], [22, 7]], 
                            [[2, 17], [22, 7]], 
                            [[2, 17], [22, 7]]]
            },
            "Fire" : {
                "Idle" : [[[0, 16], [18,16]]],
                "Hit" : [[[0, 16], [18,16]],
                            [[0, 16], [18,16]],
                            [[0, 16], [18,16]],
                            [[0, 16], [18,16]]],
                "On" : [[[0, 1], [18, 31]],
                            [[0, 2], [18,30]],
                            [[0, 4], [18,28]]]
            },
            "Fire-90" : {
                "Idle" : [[[16, 0], [18,16]]],
                "Hit" : [[[16, 0], [18,16]],
                            [[16, 0], [18,16]],
                            [[16, 0], [18,16]],
                            [[16, 0], [18,16]]],
                "On" : [[[1, 0], [33, 16]],
                            [[2, 0], [32,16]],
                            [[4, 0], [30,16]]]
            },
            "Spikes" : {
                "Idle" : [[[0, 9], [16, 7]]]
            },
            "Spikes-90" : {
                "Idle" : [[[9, 0], [7, 16]]]
            },
            "Fan" : {
                "Idle" : [[[0, -2], [24, 8]]],
                "On" : [[[0, -2], [24, 8]],
                        [[0, -2], [24, 8]],
                        [[0, -2], [24, 8]],
                        [[0, -2], [24, 8]]]
            },
            "Saw" : {
                "Idle" : [[[0, 0], [38, 38]]],
                "On" : [[[0, 0], [38, 38]],
                        [[0, 0], [38, 38]],
                        [[0, 0], [38, 38]],
                        [[0, 0], [38, 38]],
                        [[0, 0], [38, 38]],
                        [[0, 0], [38, 38]],
                        [[0, 0], [38, 38]],
                        [[0, 0], [38, 38]]],
                "Chain" : [[[0, 0], [8, 8]]]
            },
            "Spiked Ball" : {
                "Idle" : [[[0, 0], [28, 28]]],
                "Chain" : [[[0, 0], [8, 8]]]
            },
            "Falling Platforms" : {
                "Idle" : [[[0, 0], [32, 10]]],
                "On" : [[[0, 0], [32, 10]],
                        [[0, 0], [32, 10]],
                        [[0, 0], [32, 10]],
                        [[0, 0], [32, 10]]]
            },
            "Rock Head" : {
                "Idle" : [[[0, 0], [42, 42]]],
                "Blink" : [[[0, 0], [42, 42]],
                            [[0, 0], [42, 42]],
                            [[0, 0], [42, 42]],
                            [[0, 0], [42, 42]]],
                "Top Hit" : [[[0, 0], [42, 42]],
                            [[0, 0], [42, 42]],
                            [[0, 0], [42, 42]],
                            [[0, 0], [42, 42]]],
                "Left Hit" : [[[0, 0], [42, 42]],
                            [[0, 0], [42, 42]],
                            [[0, 0], [42, 42]],
                            [[0, 0], [42, 42]]],
                "Right Hit" : [[[0, 0], [42, 42]],
                            [[0, 0], [42, 42]],
                            [[0, 0], [42, 42]],
                            [[0, 0], [42, 42]]],
                "Bottom Hit" : [[[0, 0], [42, 42]],
                            [[0, 0], [42, 42]],
                            [[0, 0], [42, 42]],
                            [[0, 0], [42, 42]]]
            },
            "Spike Head" : {
                "Idle" : [[[0, 0], [54, 52]]],
                "Blink" : [[[0, 0], [54, 52]],
                            [[0, 0], [54, 52]],
                            [[0, 0], [54, 52]],
                            [[0, 0], [54, 52]]],
                "Top Hit" : [[[0, 0], [54, 52]],
                            [[0, 0], [54, 52]],
                            [[0, 0], [54, 52]],
                            [[0, 0], [54, 52]]],
                "Left Hit" : [[[0, 0], [54, 52]],
                            [[0, 0], [54, 52]],
                            [[0, 0], [54, 52]],
                            [[0, 0], [54, 52]]],
                "Right Hit" : [[[0, 0], [54, 52]],
                            [[0, 0], [54, 52]],
                            [[0, 0], [54, 52]],
                            [[0, 0], [54, 52]]],
                "Bottom Hit" : [[[0, 0], [54, 52]],
                            [[0, 0], [54, 52]],
                            [[0, 0], [54, 52]],
                            [[0, 0], [54, 52]]]
            }
        }
    }
}