{
   "land": {
      "331:557": {
         "name": "land_1",
         "type": 1,
         "flip": [
            false,
            false
         ],
         "z-index": 1,
         "values": []
      },
      "375:557": {
         "name": "land_1",
         "type": 1,
         "flip": [
            false,
            false
         ],
         "z-index": 1,
         "values": []
      },
      "419:557": {
         "name": "land_1",
         "type": 1,
         "flip": [
            false,
            false
         ],
         "z-index": 1,
         "values": []
      },
      "463:557": {
         "name": "land_1",
         "type": 1,
         "flip": [
            false,
            false
         ],
         "z-index": 1,
         "values": []
      },
      "507:557": {
         "name": "land_1",
         "type": 1,
         "flip": [
            false,
            false
         ],
         "z-index": 1,
         "values": []
      },
      "551:557": {
         "name": "land_1",
         "type": 1,
         "flip": [
            false,
            false
         ],
         "z-index": 1,
         "values": []
      },
      "595:557": {
         "name": "land_1",
         "type": 1,
         "flip": [
            false,
            false
         ],
         "z-index": 1,
         "values": []
      },
      "639:557": {
         "name": "land_1",
         "type": 1,
         "flip": [
            false,
            false
         ],
         "z-index": 1,
         "values": []
      },
      "683:557": {
         "name": "land_1",
         "type": 1,
         "flip": [
            false,
            false
         ],
         "z-index": 1,
         "values": []
      },
      "727:557": {
         "name": "land_1",
         "type": 1,
         "flip": [
            false,
            false
         ],
         "z-index": 1,
         "values": []
      },
      "771:557": {
         "name": "land_1",
         "type": 1,
         "flip": [
            false,
            false
         ],
         "z-index": 1,
         "values": []
      },
      "815:557": {
         "name": "land_1",
         "type": 1,
         "flip": [
            false,
            false
         ],
         "z-index": 1,
         "values": []
      },
      "859:557": {
         "name": "land_1",
         "type": 1,
         "flip": [
            false,
            false
         ],
         "z-index": 1,
         "values": []
      },
      "903:557": {
         "name": "land_1",
         "type": 1,
         "flip": [
            false,
            false
         ],
         "z-index": 1,
         "values": []
      },
      "947:557": {
         "name": "land_1",
         "type": 1,
         "flip": [
            false,
            false
         ],
         "z-index": 1,
         "values": []
      },
      "991:557": {
         "name": "land_1",
         "type": 1,
         "flip": [
            false,
            false
         ],
         "z-index": 1,
         "values": []
      },
      "1035:557": {
         "name": "land_1",
         "type": 1,
         "flip": [
            false,
            false
         ],
         "z-index": 1,
         "values": []
      },
      "1079:557": {
         "name": "land_1",
         "type": 1,
         "flip": [
            false,
            false
         ],
         "z-index": 1,
         "values": []
      },
      "1123:557": {
         "name": "land_1",
         "type": 1,
         "flip": [
            false,
            false
         ],
         "z-index": 1,
         "values": []
      },
      "576:527": {
         "name": "land_0",
         "type": 1,
         "flip": [
            false,
            false
         ],
         "z-index": 1,
         "values": []
      },
      "609:500": {
         "name": "land_0",
         "type": 1,
         "flip": [
            false,
            false
         ],
         "z-index": 1,
         "values": []
      },
      "643:470": {
         "name": "land_0",
         "type": 1,
         "flip": [
            false,
            false
         ],
         "z-index": 1,
         "values": []
      },
      "643:514": {
         "name": "land_11",
         "type": 1,
         "flip": [
            false,
            false
         ],
         "z-index": 1,
         "values": []
      },
      "620:540": {
         "name": "land_11",
         "type": 1,
         "flip": [
            false,
            false
         ],
         "z-index": 1,
         "values": []
      },
      "643:540": {
         "name": "land_11",
         "type": 1,
         "flip": [
            false,
            false
         ],
         "z-index": 1,
         "values": []
      },
      "620:536": {
         "name": "land_8",
         "type": 1,
         "flip": [
            false,
            false
         ],
         "z-index": 1,
         "values": []
      }
   },
   "player": {
      "649:422": {
         "name": "player",
         "type": 1,
         "flip": [
            false,
            false
         ],
         "z-index": 1,
         "values": []
      }
   },
   "items": {
      "13:527": {
         "name": "items_checkpoint",
         "type": 1,
         "flip": [
            false,
            false
         ],
         "z-index": 1,
         "values": []
      },
      "246:286": {
         "name": "items_apple",
         "type": 1,
         "flip": [
            false,
            false
         ],
         "z-index": 1,
         "values": []
      },
      "199:279": {
         "name": "items_apple",
         "type": 1,
         "flip": [
            false,
            false
         ],
         "z-index": 1,
         "values": []
      },
      "907:341": {
         "name": "items_apple",
         "type": 1,
         "flip": [
            false,
            false
         ],
         "z-index": 1,
         "values": []
      },
      "958:349": {
         "name": "items_apple",
         "type": 1,
         "flip": [
            false,
            false
         ],
         "z-index": 1,
         "values": []
      },
      "1007:340": {
         "name": "items_apple",
         "type": 1,
         "flip": [
            false,
            false
         ],
         "z-index": 1,
         "values": []
      },
      "1111:415": {
         "name": "items_apple",
         "type": 1,
         "flip": [
            false,
            false
         ],
         "z-index": 1,
         "values": []
      },
      "1134:419": {
         "name": "items_apple",
         "type": 1,
         "flip": [
            false,
            false
         ],
         "z-index": 1,
         "values": []
      },
      "745:525": {
         "name": "items_apple",
         "type": 1,
         "flip": [
            false,
            false
         ],
         "z-index": 1,
         "values": []
      },
      "784:521": {
         "name": "items_apple",
         "type": 1,
         "flip": [
            false,
            false
         ],
         "z-index": 1,
         "values": []
      },
      "826:521": {
         "name": "items_apple",
         "type": 1,
         "flip": [
            false,
            false
         ],
         "z-index": 1,
         "values": []
      },
      "759:477": {
         "name": "items_box1",
         "type": 1,
         "flip": [
            false,
            false
         ],
         "z-index": 1,
         "values": []
      },
      "801:475": {
         "name": "items_box2",
         "type": 1,
         "flip": [
            false,
            false
         ],
         "z-index": 1,
         "values": []
      },
      "848:477": {
         "name": "items_box3",
         "type": 1,
         "flip": [
            false,
            false
         ],
         "z-index": 1,
         "values": []
      },
      "959:514": {
         "name": "items_cherries",
         "type": 1,
         "flip": [
            false,
            false
         ],
         "z-index": 1,
         "values": []
      },
      "402:471": {
         "name": "items_cherries",
         "type": 1,
         "flip": [
            false,
            false
         ],
         "z-index": 1,
         "values": []
      },
      "257:253": {
         "name": "items_cherries",
         "type": 1,
         "flip": [
            false,
            false
         ],
         "z-index": 1,
         "values": []
      },
      "234:253": {
         "name": "items_cherries",
         "type": 1,
         "flip": [
            false,
            false
         ],
         "z-index": 1,
         "values": []
      },
      "-7:342": {
         "name": "items_melon",
         "type": 1,
         "flip": [
            false,
            false
         ],
         "z-index": 1,
         "values": []
      },
      "30:340": {
         "name": "items_strawberry",
         "type": 1,
         "flip": [
            false,
            false
         ],
         "z-index": 1,
         "values": []
      },
      "317:360": {
         "name": "items_strawberry",
         "type": 1,
         "flip": [
            false,
            false
         ],
         "z-index": 1,
         "values": []
      },
      "265:364": {
         "name": "items_pineapple",
         "type": 1,
         "flip": [
            false,
            false
         ],
         "z-index": 1,
         "values": []
      },
      "375:468": {
         "name": "items_orange",
         "type": 1,
         "flip": [
            false,
            false
         ],
         "z-index": 1,
         "values": []
      },
      "394:498": {
         "name": "items_orange",
         "type": 1,
         "flip": [
            false,
            false
         ],
         "z-index": 1,
         "values": []
      },
      "609:463": {
         "name": "items_bananas",
         "type": 1,
         "flip": [
            false,
            false
         ],
         "z-index": 1,
         "values": []
      },
      "581:487": {
         "name": "items_bananas",
         "type": 1,
         "flip": [
            false,
            false
         ],
         "z-index": 1,
         "values": []
      },
      "747:409": {
         "name": "items_bananas",
         "type": 1,
         "flip": [
            false,
            false
         ],
         "z-index": 1,
         "values": []
      },
      "791:408": {
         "name": "items_bananas",
         "type": 1,
         "flip": [
            false,
            false
         ],
         "z-index": 1,
         "values": []
      },
      "835:409": {
         "name": "items_bananas",
         "type": 1,
         "flip": [
            false,
            false
         ],
         "z-index": 1,
         "values": []
      },
      "1088:347": {
         "name": "items_bananas",
         "type": 1,
         "flip": [
            false,
            false
         ],
         "z-index": 1,
         "values": []
      },
      "1124:349": {
         "name": "items_bananas",
         "type": 1,
         "flip": [
            false,
            false
         ],
         "z-index": 1,
         "values": []
      },
      "1085:304": {
         "name": "items_bananas",
         "type": 1,
         "flip": [
            false,
            false
         ],
         "z-index": 1,
         "values": []
      },
      "1125:312": {
         "name": "items_bananas",
         "type": 1,
         "flip": [
            false,
            false
         ],
         "z-index": 1,
         "values": []
      },
      "988:515": {
         "name": "items_bananas",
         "type": 1,
         "flip": [
            false,
            false
         ],
         "z-index": 1,
         "values": []
      },
      "1016:515": {
         "name": "items_bananas",
         "type": 1,
         "flip": [
            false,
            false
         ],
         "z-index": 1,
         "values": []
      },
      "1018:485": {
         "name": "items_bananas",
         "type": 1,
         "flip": [
            false,
            false
         ],
         "z-index": 1,
         "values": []
      },
      "985:481": {
         "name": "items_bananas",
         "type": 1,
         "flip": [
            false,
            false
         ],
         "z-index": 1,
         "values": []
      },
      "955:475": {
         "name": "items_bananas",
         "type": 1,
         "flip": [
            false,
            false
         ],
         "z-index": 1,
         "values": []
      },
      "541:524": {
         "name": "items_bananas",
         "type": 1,
         "flip": [
            false,
            false
         ],
         "z-index": 1,
         "values": []
      },
      "514:523": {
         "name": "items_bananas",
         "type": 1,
         "flip": [
            false,
            false
         ],
         "z-index": 1,
         "values": []
      },
      "908:382": {
         "name": "items_bananas",
         "type": 1,
         "flip": [
            false,
            false
         ],
         "z-index": 1,
         "values": []
      },
      "967:386": {
         "name": "items_bananas",
         "type": 1,
         "flip": [
            false,
            false
         ],
         "z-index": 1,
         "values": []
      },
      "1008:371": {
         "name": "items_bananas",
         "type": 1,
         "flip": [
            false,
            false
         ],
         "z-index": 1,
         "values": []
      },
      "694:516": {
         "name": "items_bananas",
         "type": 1,
         "flip": [
            false,
            false
         ],
         "z-index": 1,
         "values": []
      },
      "697:485": {
         "name": "items_bananas",
         "type": 1,
         "flip": [
            false,
            false
         ],
         "z-index": 1,
         "values": []
      },
      "700:450": {
         "name": "items_bananas",
         "type": 1,
         "flip": [
            false,
            false
         ],
         "z-index": 1,
         "values": []
      }
   },
   "traps": {
      "401:527": {
         "name": "traps_trampoline",
         "type": 1,
         "flip": [
            false,
            false
         ],
         "z-index": 1,
         "values": []
      },
      "188:352": {
         "name": "traps_rockhead",
         "type": 1,
         "flip": [
            false,
            false
         ],
         "z-index": 1,
         "values": [
            "1",
            "2"
         ]
      },
      "461:473": {
         "name": "traps_spikedball",
         "type": 1,
         "flip": [
            false,
            false
         ],
         "z-index": 1,
         "values": [
            "1",
            "2",
            "120",
            "4"
         ]
      },
      "370:525": {
         "name": "traps_fire",
         "type": 1,
         "flip": [
            false,
            false
         ],
         "z-index": 1,
         "values": []
      },
      "472:383": {
         "name": "traps_spikedball",
         "type": 1,
         "flip": [
            false,
            false
         ],
         "z-index": 1,
         "values": [
            "1",
            "1"
         ]
      },
      "429:328": {
         "name": "traps_saw",
         "type": 1,
         "flip": [
            false,
            false
         ],
         "z-index": 1,
         "values": [
            "1",
            "1"
         ]
      },
      "1109:448": {
         "name": "traps_blocks",
         "type": 1,
         "flip": [
            false,
            false
         ],
         "z-index": 1,
         "values": []
      },
      "1136:449": {
         "name": "traps_blocks",
         "type": 1,
         "flip": [
            false,
            false
         ],
         "z-index": 1,
         "values": []
      },
      "968:433": {
         "name": "traps_arrow",
         "type": 1,
         "flip": [
            false,
            false
         ],
         "z-index": 1,
         "values": []
      },
      "1017:427": {
         "name": "traps_arrow",
         "type": 1,
         "flip": [
            false,
            false
         ],
         "z-index": 1,
         "values": []
      },
      "913:435": {
         "name": "traps_arrow",
         "type": 1,
         "flip": [
            false,
            false
         ],
         "z-index": 1,
         "values": []
      },
      "887:505": {
         "name": "traps_spikehead",
         "type": 1,
         "flip": [
            false,
            false
         ],
         "z-index": 1,
         "values": [
            "1",
            "2"
         ]
      },
      "694:549": {
         "name": "traps_fan",
         "type": 1,
         "flip": [
            false,
            false
         ],
         "z-index": 1,
         "values": []
      },
      "33:412": {
         "name": "traps_arrow",
         "type": 1,
         "flip": [
            false,
            false
         ],
         "z-index": 1,
         "values": []
      },
      "33:469": {
         "name": "traps_arrow",
         "type": 1,
         "flip": [
            false,
            false
         ],
         "z-index": 1,
         "values": []
      },
      "29:508": {
         "name": "traps_arrow",
         "type": 1,
         "flip": [
            false,
            false
         ],
         "z-index": 1,
         "values": []
      },
      "-6:440": {
         "name": "traps_arrow",
         "type": 1,
         "flip": [
            false,
            false
         ],
         "z-index": 1,
         "values": []
      },
      "63:442": {
         "name": "traps_arrow",
         "type": 1,
         "flip": [
            false,
            false
         ],
         "z-index": 1,
         "values": []
      },
      "61:489": {
         "name": "traps_arrow",
         "type": 1,
         "flip": [
            false,
            false
         ],
         "z-index": 1,
         "values": []
      },
      "6:487": {
         "name": "traps_arrow",
         "type": 1,
         "flip": [
            false,
            false
         ],
         "z-index": 1,
         "values": []
      },
      "578:329": {
         "name": "traps_saw",
         "type": 1,
         "flip": [
            false,
            false
         ],
         "z-index": 1,
         "values": [
            "2",
            "1"
         ]
      },
      "845:325": {
         "name": "traps_saw",
         "type": 1,
         "flip": [
            false,
            false
         ],
         "z-index": 1,
         "values": [
            "2",
            "2"
         ]
      }
   },
   "block": {
      "322:584": {
         "name": "block_22",
         "type": 1,
         "flip": [
            false,
            false
         ],
         "z-index": 1,
         "values": []
      },
      "322:567": {
         "name": "block_22",
         "type": 1,
         "flip": [
            false,
            false
         ],
         "z-index": 1,
         "values": []
      },
      "322:550": {
         "name": "block_22",
         "type": 1,
         "flip": [
            false,
            false
         ],
         "z-index": 1,
         "values": []
      },
      "331:540": {
         "name": "block_22",
         "type": 1,
         "flip": [
            false,
            false
         ],
         "z-index": 1,
         "values": []
      },
      "331:523": {
         "name": "block_22",
         "type": 1,
         "flip": [
            false,
            false
         ],
         "z-index": 1,
         "values": []
      },
      "331:506": {
         "name": "block_22",
         "type": 1,
         "flip": [
            false,
            false
         ],
         "z-index": 1,
         "values": []
      },
      "331:489": {
         "name": "block_22",
         "type": 1,
         "flip": [
            false,
            false
         ],
         "z-index": 1,
         "values": []
      },
      "331:472": {
         "name": "block_22",
         "type": 1,
         "flip": [
            false,
            false
         ],
         "z-index": 1,
         "values": []
      },
      "331:455": {
         "name": "block_22",
         "type": 1,
         "flip": [
            false,
            false
         ],
         "z-index": 1,
         "values": []
      },
      "331:438": {
         "name": "block_22",
         "type": 1,
         "flip": [
            false,
            false
         ],
         "z-index": 1,
         "values": []
      },
      "331:421": {
         "name": "block_22",
         "type": 1,
         "flip": [
            false,
            false
         ],
         "z-index": 1,
         "values": []
      },
      "159:236": {
         "name": "block_2",
         "type": 1,
         "flip": [
            false,
            false
         ],
         "z-index": 1,
         "values": []
      },
      "206:236": {
         "name": "block_2",
         "type": 1,
         "flip": [
            false,
            false
         ],
         "z-index": 1,
         "values": []
      },
      "253:236": {
         "name": "block_2",
         "type": 1,
         "flip": [
            false,
            false
         ],
         "z-index": 1,
         "values": []
      },
      "300:234": {
         "name": "block_23",
         "type": 1,
         "flip": [
            false,
            false
         ],
         "z-index": 1,
         "values": []
      },
      "175:245": {
         "name": "block_23",
         "type": 1,
         "flip": [
            false,
            false
         ],
         "z-index": 1,
         "values": []
      },
      "330:404": {
         "name": "block_12",
         "type": 1,
         "flip": [
            false,
            false
         ],
         "z-index": 1,
         "values": []
      }
   },
   "metal": {
      "283:405": {
         "name": "metal_0",
         "type": 1,
         "flip": [
            false,
            false
         ],
         "z-index": 1,
         "values": []
      },
      "235:405": {
         "name": "metal_0",
         "type": 1,
         "flip": [
            false,
            false
         ],
         "z-index": 1,
         "values": []
      },
      "187:405": {
         "name": "metal_0",
         "type": 1,
         "flip": [
            false,
            false
         ],
         "z-index": 1,
         "values": []
      },
      "139:405": {
         "name": "metal_0",
         "type": 1,
         "flip": [
            false,
            false
         ],
         "z-index": 1,
         "values": []
      },
      "91:405": {
         "name": "metal_0",
         "type": 1,
         "flip": [
            false,
            false
         ],
         "z-index": 1,
         "values": []
      },
      "91:421": {
         "name": "metal_5",
         "type": 1,
         "flip": [
            false,
            false
         ],
         "z-index": 1,
         "values": []
      },
      "91:469": {
         "name": "metal_5",
         "type": 1,
         "flip": [
            false,
            false
         ],
         "z-index": 1,
         "values": []
      },
      "91:517": {
         "name": "metal_5",
         "type": 1,
         "flip": [
            false,
            false
         ],
         "z-index": 1,
         "values": []
      },
      "91:565": {
         "name": "metal_5",
         "type": 1,
         "flip": [
            false,
            false
         ],
         "z-index": 1,
         "values": []
      },
      "238:323": {
         "name": "metal_0",
         "type": 1,
         "flip": [
            false,
            false
         ],
         "z-index": 1,
         "values": []
      },
      "286:323": {
         "name": "metal_0",
         "type": 1,
         "flip": [
            false,
            false
         ],
         "z-index": 1,
         "values": []
      },
      "334:323": {
         "name": "metal_0",
         "type": 1,
         "flip": [
            false,
            false
         ],
         "z-index": 1,
         "values": []
      },
      "128:323": {
         "name": "metal_0",
         "type": 1,
         "flip": [
            false,
            false
         ],
         "z-index": 1,
         "values": []
      },
      "80:323": {
         "name": "metal_0",
         "type": 1,
         "flip": [
            false,
            false
         ],
         "z-index": 1,
         "values": []
      },
      "32:323": {
         "name": "metal_0",
         "type": 1,
         "flip": [
            false,
            false
         ],
         "z-index": 1,
         "values": []
      },
      "-16:323": {
         "name": "metal_0",
         "type": 1,
         "flip": [
            false,
            false
         ],
         "z-index": 1,
         "values": []
      },
      "-32:323": {
         "name": "metal_5",
         "type": 1,
         "flip": [
            false,
            false
         ],
         "z-index": 1,
         "values": []
      },
      "-32:371": {
         "name": "metal_5",
         "type": 1,
         "flip": [
            false,
            false
         ],
         "z-index": 1,
         "values": []
      },
      "-32:419": {
         "name": "metal_5",
         "type": 1,
         "flip": [
            false,
            false
         ],
         "z-index": 1,
         "values": []
      },
      "-32:467": {
         "name": "metal_5",
         "type": 1,
         "flip": [
            false,
            false
         ],
         "z-index": 1,
         "values": []
      },
      "-32:515": {
         "name": "metal_5",
         "type": 1,
         "flip": [
            false,
            false
         ],
         "z-index": 1,
         "values": []
      },
      "-32:563": {
         "name": "metal_5",
         "type": 1,
         "flip": [
            false,
            false
         ],
         "z-index": 1,
         "values": []
      },
      "-16:595": {
         "name": "metal_0",
         "type": 1,
         "flip": [
            false,
            false
         ],
         "z-index": 1,
         "values": []
      },
      "32:595": {
         "name": "metal_0",
         "type": 1,
         "flip": [
            false,
            false
         ],
         "z-index": 1,
         "values": []
      },
      "80:595": {
         "name": "metal_9",
         "type": 1,
         "flip": [
            false,
            false
         ],
         "z-index": 1,
         "values": []
      },
      "382:291": {
         "name": "metal_5",
         "type": 1,
         "flip": [
            false,
            false
         ],
         "z-index": 1,
         "values": []
      },
      "1166:291": {
         "name": "metal_5",
         "type": 1,
         "flip": [
            false,
            false
         ],
         "z-index": 1,
         "values": []
      },
      "1166:339": {
         "name": "metal_5",
         "type": 1,
         "flip": [
            false,
            false
         ],
         "z-index": 1,
         "values": []
      },
      "1166:387": {
         "name": "metal_5",
         "type": 1,
         "flip": [
            false,
            false
         ],
         "z-index": 1,
         "values": []
      },
      "1166:435": {
         "name": "metal_5",
         "type": 1,
         "flip": [
            false,
            false
         ],
         "z-index": 1,
         "values": []
      },
      "1166:483": {
         "name": "metal_5",
         "type": 1,
         "flip": [
            false,
            false
         ],
         "z-index": 1,
         "values": []
      },
      "1166:531": {
         "name": "metal_5",
         "type": 1,
         "flip": [
            false,
            false
         ],
         "z-index": 1,
         "values": []
      },
      "1087:456": {
         "name": "metal_5",
         "type": 1,
         "flip": [
            false,
            false
         ],
         "z-index": 1,
         "values": []
      },
      "1087:408": {
         "name": "metal_5",
         "type": 1,
         "flip": [
            false,
            false
         ],
         "z-index": 1,
         "values": []
      },
      "1087:392": {
         "name": "metal_0",
         "type": 1,
         "flip": [
            false,
            false
         ],
         "z-index": 1,
         "values": []
      },
      "1121:392": {
         "name": "metal_0",
         "type": 1,
         "flip": [
            false,
            false
         ],
         "z-index": 1,
         "values": []
      },
      "159:277": {
         "name": "metal_5",
         "type": 1,
         "flip": [
            false,
            false
         ],
         "z-index": 1,
         "values": []
      },
      "294:275": {
         "name": "metal_5",
         "type": 1,
         "flip": [
            false,
            false
         ],
         "z-index": 1,
         "values": []
      },
      "468:380": {
         "name": "metal_9",
         "type": 1,
         "flip": [
            false,
            false
         ],
         "z-index": 5,
         "values": []
      },
      "746:450": {
         "name": "metal_3",
         "type": 1,
         "flip": [
            false,
            false
         ],
         "z-index": 1,
         "values": []
      },
      "794:450": {
         "name": "metal_3",
         "type": 1,
         "flip": [
            false,
            false
         ],
         "z-index": 1,
         "values": []
      },
      "842:450": {
         "name": "metal_3",
         "type": 1,
         "flip": [
            false,
            false
         ],
         "z-index": 1,
         "values": []
      },
      "159:261": {
         "name": "metal_9",
         "type": 1,
         "flip": [
            false,
            false
         ],
         "z-index": 1,
         "values": []
      },
      "159:245": {
         "name": "metal_9",
         "type": 1,
         "flip": [
            false,
            false
         ],
         "z-index": 1,
         "values": []
      },
      "294:259": {
         "name": "metal_9",
         "type": 1,
         "flip": [
            false,
            false
         ],
         "z-index": 1,
         "values": []
      },
      "294:243": {
         "name": "metal_9",
         "type": 1,
         "flip": [
            false,
            false
         ],
         "z-index": 1,
         "values": []
      }
   },
   "wall": {},
   "blockgray": {
      "398:291": {
         "name": "blockgray_4",
         "type": 1,
         "flip": [
            false,
            false
         ],
         "z-index": 1,
         "values": []
      },
      "414:291": {
         "name": "blockgray_4",
         "type": 1,
         "flip": [
            false,
            false
         ],
         "z-index": 1,
         "values": []
      },
      "430:291": {
         "name": "blockgray_4",
         "type": 1,
         "flip": [
            false,
            false
         ],
         "z-index": 1,
         "values": []
      },
      "446:291": {
         "name": "blockgray_4",
         "type": 1,
         "flip": [
            false,
            false
         ],
         "z-index": 1,
         "values": []
      },
      "462:291": {
         "name": "blockgray_4",
         "type": 1,
         "flip": [
            false,
            false
         ],
         "z-index": 1,
         "values": []
      },
      "478:291": {
         "name": "blockgray_4",
         "type": 1,
         "flip": [
            false,
            false
         ],
         "z-index": 1,
         "values": []
      },
      "494:291": {
         "name": "blockgray_4",
         "type": 1,
         "flip": [
            false,
            false
         ],
         "z-index": 1,
         "values": []
      },
      "510:291": {
         "name": "blockgray_4",
         "type": 1,
         "flip": [
            false,
            false
         ],
         "z-index": 1,
         "values": []
      },
      "526:291": {
         "name": "blockgray_4",
         "type": 1,
         "flip": [
            false,
            false
         ],
         "z-index": 1,
         "values": []
      },
      "542:291": {
         "name": "blockgray_4",
         "type": 1,
         "flip": [
            false,
            false
         ],
         "z-index": 1,
         "values": []
      },
      "558:291": {
         "name": "blockgray_4",
         "type": 1,
         "flip": [
            false,
            false
         ],
         "z-index": 1,
         "values": []
      },
      "574:291": {
         "name": "blockgray_4",
         "type": 1,
         "flip": [
            false,
            false
         ],
         "z-index": 1,
         "values": []
      },
      "590:291": {
         "name": "blockgray_4",
         "type": 1,
         "flip": [
            false,
            false
         ],
         "z-index": 1,
         "values": []
      },
      "606:291": {
         "name": "blockgray_4",
         "type": 1,
         "flip": [
            false,
            false
         ],
         "z-index": 1,
         "values": []
      },
      "622:291": {
         "name": "blockgray_4",
         "type": 1,
         "flip": [
            false,
            false
         ],
         "z-index": 1,
         "values": []
      },
      "638:291": {
         "name": "blockgray_4",
         "type": 1,
         "flip": [
            false,
            false
         ],
         "z-index": 1,
         "values": []
      },
      "654:291": {
         "name": "blockgray_4",
         "type": 1,
         "flip": [
            false,
            false
         ],
         "z-index": 1,
         "values": []
      },
      "670:291": {
         "name": "blockgray_4",
         "type": 1,
         "flip": [
            false,
            false
         ],
         "z-index": 1,
         "values": []
      },
      "686:291": {
         "name": "blockgray_4",
         "type": 1,
         "flip": [
            false,
            false
         ],
         "z-index": 1,
         "values": []
      },
      "702:291": {
         "name": "blockgray_4",
         "type": 1,
         "flip": [
            false,
            false
         ],
         "z-index": 1,
         "values": []
      },
      "718:291": {
         "name": "blockgray_4",
         "type": 1,
         "flip": [
            false,
            false
         ],
         "z-index": 1,
         "values": []
      },
      "734:291": {
         "name": "blockgray_4",
         "type": 1,
         "flip": [
            false,
            false
         ],
         "z-index": 1,
         "values": []
      },
      "750:291": {
         "name": "blockgray_4",
         "type": 1,
         "flip": [
            false,
            false
         ],
         "z-index": 1,
         "values": []
      },
      "766:291": {
         "name": "blockgray_4",
         "type": 1,
         "flip": [
            false,
            false
         ],
         "z-index": 1,
         "values": []
      },
      "782:291": {
         "name": "blockgray_4",
         "type": 1,
         "flip": [
            false,
            false
         ],
         "z-index": 1,
         "values": []
      },
      "798:291": {
         "name": "blockgray_4",
         "type": 1,
         "flip": [
            false,
            false
         ],
         "z-index": 1,
         "values": []
      },
      "814:291": {
         "name": "blockgray_4",
         "type": 1,
         "flip": [
            false,
            false
         ],
         "z-index": 1,
         "values": []
      },
      "830:291": {
         "name": "blockgray_4",
         "type": 1,
         "flip": [
            false,
            false
         ],
         "z-index": 1,
         "values": []
      },
      "846:291": {
         "name": "blockgray_4",
         "type": 1,
         "flip": [
            false,
            false
         ],
         "z-index": 1,
         "values": []
      },
      "862:291": {
         "name": "blockgray_4",
         "type": 1,
         "flip": [
            false,
            false
         ],
         "z-index": 1,
         "values": []
      },
      "878:291": {
         "name": "blockgray_4",
         "type": 1,
         "flip": [
            false,
            false
         ],
         "z-index": 1,
         "values": []
      },
      "894:291": {
         "name": "blockgray_4",
         "type": 1,
         "flip": [
            false,
            false
         ],
         "z-index": 1,
         "values": []
      },
      "910:291": {
         "name": "blockgray_4",
         "type": 1,
         "flip": [
            false,
            false
         ],
         "z-index": 1,
         "values": []
      },
      "926:291": {
         "name": "blockgray_4",
         "type": 1,
         "flip": [
            false,
            false
         ],
         "z-index": 1,
         "values": []
      },
      "942:291": {
         "name": "blockgray_4",
         "type": 1,
         "flip": [
            false,
            false
         ],
         "z-index": 1,
         "values": []
      },
      "958:291": {
         "name": "blockgray_4",
         "type": 1,
         "flip": [
            false,
            false
         ],
         "z-index": 1,
         "values": []
      },
      "974:291": {
         "name": "blockgray_4",
         "type": 1,
         "flip": [
            false,
            false
         ],
         "z-index": 1,
         "values": []
      },
      "990:291": {
         "name": "blockgray_4",
         "type": 1,
         "flip": [
            false,
            false
         ],
         "z-index": 1,
         "values": []
      },
      "1006:291": {
         "name": "blockgray_4",
         "type": 1,
         "flip": [
            false,
            false
         ],
         "z-index": 1,
         "values": []
      },
      "1022:291": {
         "name": "blockgray_4",
         "type": 1,
         "flip": [
            false,
            false
         ],
         "z-index": 1,
         "values": []
      },
      "1038:291": {
         "name": "blockgray_4",
         "type": 1,
         "flip": [
            false,
            false
         ],
         "z-index": 1,
         "values": []
      },
      "1054:291": {
         "name": "blockgray_4",
         "type": 1,
         "flip": [
            false,
            false
         ],
         "z-index": 1,
         "values": []
      },
      "1070:291": {
         "name": "blockgray_4",
         "type": 1,
         "flip": [
            false,
            false
         ],
         "z-index": 1,
         "values": []
      },
      "1086:291": {
         "name": "blockgray_4",
         "type": 1,
         "flip": [
            false,
            false
         ],
         "z-index": 1,
         "values": []
      },
      "1102:291": {
         "name": "blockgray_4",
         "type": 1,
         "flip": [
            false,
            false
         ],
         "z-index": 1,
         "values": []
      },
      "1118:291": {
         "name": "blockgray_4",
         "type": 1,
         "flip": [
            false,
            false
         ],
         "z-index": 1,
         "values": []
      },
      "1134:291": {
         "name": "blockgray_4",
         "type": 1,
         "flip": [
            false,
            false
         ],
         "z-index": 1,
         "values": []
      },
      "1150:291": {
         "name": "blockgray_4",
         "type": 1,
         "flip": [
            false,
            false
         ],
         "z-index": 1,
         "values": []
      }
   },
   "line": {
      "384:431": {
         "name": "line_1",
         "type": 2,
         "flip": [
            false,
            false
         ],
         "z-index": 1,
         "values": []
      }
   }
}